mypy_helper/__init__.py
mypy_helper/__main__.py
mypy_helper/fix_ignore_without_code.py
mypy_helper/py.typed
mypy_helper/pytest_fixture_type_gen.py
mypy_helper-0.1.1.dist-info/LICENSE
mypy_helper-0.1.1.dist-info/METADATA
mypy_helper-0.1.1.dist-info/WHEEL
mypy_helper-0.1.1.dist-info/entry_points.txt
mypy_helper-0.1.1.dist-info/RECORD
